[
  {
    "index": 1,
    "MessageID": 99481,
    "TextENGNew": "\"After them! Don't let them escape!\"",
    "significantChanges": false
  },
  {
    "index": 2,
    "MessageID": 99482,
    "TextENGNew": "The gruff shouts of police officers echoed from the garden.",
    "significantChanges": false
  },
  {
    "index": 3,
    "MessageID": 99483,
    "TextENGNew": "The back room next door had fallen silent.",
    "significantChanges": false
  },
  {
    "index": 4,
    "MessageID": 99484,
    "TextENGNew": "When I gently slid open the fusuma, I found Miyuki-chan on the other side, cuffing the men in black one after another.",
    "significantChanges": false
  },
  {
    "index": 5,
    "MessageID": 99485,
    "TextENGNew": "Detectives sprinted after several of the black-suited men who'd fled toward the garden.",
    "significantChanges": false
  },
  {
    "index": 6,
    "MessageID": 99486,
    "TextENGNew": "\"Phew... I'll leave the rest to you.\"",
    "significantChanges": false
  },
  {
    "index": 7,
    "MessageID": 99487,
    "TextENGNew": "Miyuki-chan called out to the officers beside her, and the handcuffed men were passed off to other detectives and led out of the back room.",
    "significantChanges": false
  },
  {
    "index": 8,
    "MessageID": 99488,
    "TextENGNew": "...Before I even realized it, everything was over.",
    "significantChanges": false
  },
  {
    "index": 9,
    "MessageID": 99489,
    "TextENGNew": "\"Miyuki-chan...\"",
    "significantChanges": false
  },
  {
    "index": 10,
    "MessageID": 99490,
    "TextENGNew": "\"Ryuunosuke-san... are you hurt?\"",
    "significantChanges": false
  },
  {
    "index": 11,
    "MessageID": 99491,
    "TextENGNew": "\"Oh no, blood...?!\"",
    "significantChanges": false
  },
  {
    "index": 12,
    "MessageID": 99492,
    "TextENGNew": "Miyuki-chan rushed over to check on me.",
    "significantChanges": false
  },
  {
    "index": 13,
    "MessageID": 99493,
    "TextENGNew": "She wiped the blood from the tip of my nose with her fingertips, then cupped my cheeks in both hands and peered intently into my face.",
    "significantChanges": false
  },
  {
    "index": 14,
    "MessageID": 99494,
    "TextENGNew": "So much had happened since I first met Miyuki-chan yesterday morning, but... looking at her now, right here in front of me, she was still as cute as ever.",
    "significantChanges": false
  },
  {
    "index": 15,
    "MessageID": 99495,
    "TextENGNew": "\"I'm sorry for putting you through all of this, Ryuunosuke-san.@k@vS10/40/410300971. I wanted to get here sooner, but...\"",
    "significantChanges": false
  },
  {
    "index": 16,
    "MessageID": 99496,
    "TextENGNew": "\"It's all right.@k@vS10/62/410101689. I was totally fine.@k@vS10/62/410101690. ...More importantly, I'm sorry about all this.@k@vS10/62/410101691. I wish we could've straightened everything out before you got here, Miyuki-chan...\"",
    "significantChanges": false
  },
  {
    "index": 17,
    "MessageID": 99497,
    "TextENGNew": "\"What are you talking about?!@k@vS10/40/410300973. Isn't this exactly the sort of situation you should rely on the power of the state for?!\"",
    "significantChanges": false
  },
  {
    "index": 18,
    "MessageID": 99498,
    "TextENGNew": "Miyuki-chan flashed a friendly smile.",
    "significantChanges": false
  },
  {
    "index": 19,
    "MessageID": 99499,
    "TextENGNew": "Her smiling face seemed to soothe all my pain and weariness.",
    "significantChanges": false
  },
  {
    "index": 20,
    "MessageID": 99500,
    "TextENGNew": "All the muscles in my body loosened up, and I felt comfortable enough that I wouldn't even regret it if I died here.",
    "significantChanges": false
  },
  {
    "index": 21,
    "MessageID": 99501,
    "TextENGNew": "I wasn't sure if my feelings were able to get through to her, but Miyuki-chan looked back at me with a huge smile.",
    "significantChanges": false
  },
  {
    "index": 22,
    "MessageID": 99502,
    "TextENGNew": "\"Hey... Miyuki-chan...@k@vS10/62/410101693. About... that promise...\"",
    "significantChanges": false
  },
  {
    "index": 23,
    "MessageID": 99503,
    "TextENGNew": "\"Huh?\"",
    "significantChanges": false
  },
  {
    "index": 24,
    "MessageID": 99504,
    "TextENGNew": "\"No, I mean...\"",
    "significantChanges": false
  },
  {
    "index": 25,
    "MessageID": 99505,
    "TextENGNew": "I continued to stammer as Miyuki-chan gazed at me.",
    "significantChanges": false
  },
  {
    "index": 26,
    "MessageID": 99506,
    "TextENGNew": "She looked like she was just waiting for the words to come out... but I suddenly started to feel embarrassed and turned away.",
    "significantChanges": false
  },
  {
    "index": 27,
    "MessageID": 99507,
    "TextENGNew": "...What am I doing acting like some naive middle school boy?! Don't forget how old you are!!",
    "significantChanges": false
  },
  {
    "index": 28,
    "MessageID": 99508,
    "TextENGNew": "Well, that's all right. ...At any rate... being good friends seems like a nice place to start...",
    "significantChanges": false
  },
  {
    "index": 29,
    "MessageID": 99509,
    "TextENGNew": "\"Umm... anyway...\"",
    "significantChanges": false
  },
  {
    "index": 30,
    "MessageID": 99510,
    "TextENGNew": "\"Ryuunosuke-san, what's wrong...?@k@vS10/40/410300976. Are you all right...?\"",
    "significantChanges": false
  },
  {
    "index": 31,
    "MessageID": 99511,
    "TextENGNew": "Miyuki-chan held my hand tight while firmly gazing into my eyes.",
    "significantChanges": false
  },
  {
    "index": 32,
    "MessageID": 99512,
    "TextENGNew": "Could it be...? Is that handhold an invitation?!",
    "significantChanges": false
  },
  {
    "index": 33,
    "MessageID": 99513,
    "TextENGNew": "My heart was beating far more intensely than usual.",
    "significantChanges": false
  },
  {
    "index": 34,
    "MessageID": 99514,
    "TextENGNew": "But it was a totally different sort of tension from the gun battle earlier. It felt good.",
    "significantChanges": false
  },
  {
    "index": 35,
    "MessageID": 99515,
    "TextENGNew": "\"Miyuki-chan...\"",
    "significantChanges": false
  },
  {
    "index": 36,
    "MessageID": 99516,
    "TextENGNew": "\"Ryuunosuke-san...\"",
    "significantChanges": false
  },
  {
    "index": 37,
    "MessageID": 99517,
    "TextENGNew": "With Miyuki-chan gazing up at me with a slight blush in her cheeks, my heart started beating so violently it felt like it was going to burst out of my body.",
    "significantChanges": false
  },
  {
    "index": 38,
    "MessageID": 99518,
    "TextENGNew": "\"Miyuki-chan...\"",
    "significantChanges": false
  },
  {
    "index": 39,
    "MessageID": 99519,
    "TextENGNew": "Come on, now's your chance!",
    "significantChanges": false
  },
  {
    "index": 40,
    "MessageID": 99520,
    "TextENGNew": "I pulled Miyuki-chan's hand in closer, and with determination...",
    "significantChanges": false
  },
  {
    "index": 41,
    "MessageID": 99521,
    "TextENGNew": "\"...What are you doing with my daughter?\"",
    "significantChanges": false
  },
  {
    "index": 42,
    "MessageID": 99522,
    "TextENGNew": "\"Aaah?!\"",
    "significantChanges": false
  },
  {
    "index": 43,
    "MessageID": 99523,
    "TextENGNew": "I heard a gruff voice coming from behind, and quickly let go of Miyuki-chan's hand.",
    "significantChanges": false
  },
  {
    "index": 44,
    "MessageID": 99524,
    "TextENGNew": "When I turned in that direction, a tall, slender man dressed in a suit put a hand on Miyuki-chan's shoulder and stared at me over his shoulder.",
    "significantChanges": false
  },
  {
    "index": 45,
    "MessageID": 99525,
    "TextENGNew": "\"Dad...?!\"",
    "significantChanges": false
  },
  {
    "index": 46,
    "MessageID": 99526,
    "TextENGNew": "\"D...a...d...?!\"",
    "significantChanges": false
  },
  {
    "index": 47,
    "MessageID": 99527,
    "TextENGNew": "\"Hello there.@k@vS10/13/410900003. I'm her father.\"",
    "significantChanges": false
  },
  {
    "index": 48,
    "MessageID": 99528,
    "TextENGNew": "...His frightening eyes were glaring straight at me, causing me to freeze up for a totally different reason this time.",
    "significantChanges": false
  },
  {
    "index": 49,
    "MessageID": 99529,
    "TextENGNew": "In other words, it was... hair-raising.",
    "significantChanges": false
  },
  {
    "index": 50,
    "MessageID": 99530,
    "TextENGNew": "\"Uh, well then, umm,@k@|@y@vS10/62/410101701. ...huh?!\"",
    "significantChanges": false
  },
  {
    "index": 51,
    "MessageID": 99531,
    "TextENGNew": "\"Aren't you... Akasaka-san?!\"",
    "significantChanges": false
  },
  {
    "index": 52,
    "MessageID": 99532,
    "TextENGNew": "I remember now. ...I'm certain that was the detective from the Metropolitan police department that I met while investigating the Hinamizawa tapes my father left behind.",
    "significantChanges": false
  },
  {
    "index": 53,
    "MessageID": 99533,
    "TextENGNew": "Akasaka-san seems to have changed a bit since I first met him. It's like he was more dignified, solemn, awe-inspiring, and refined...",
    "significantChanges": false
  },
  {
    "index": 54,
    "MessageID": 99534,
    "TextENGNew": "But... what was Akasaka-san doing in Hinamizawa again...?",
    "significantChanges": false
  },
  {
    "index": 55,
    "MessageID": 99535,
    "TextENGNew": "\"Huh...?@k@vS10/13/410900005. Might you be... Arakawa-kun?\"",
    "significantChanges": false
  },
  {
    "index": 56,
    "MessageID": 99536,
    "TextENGNew": "\"Y-yes, that's right.\"",
    "significantChanges": false
  },
  {
    "index": 57,
    "MessageID": 99537,
    "TextENGNew": "\"Oh, it's you?@k@vS10/13/410900007. And here I thought you were some daredevil making a pass on my daughter.@k@vS10/13/410900008. I'm sorry, forgive my rudeness.\"",
    "significantChanges": false
  },
  {
    "index": 58,
    "MessageID": 99538,
    "TextENGNew": "\"Hah, haha...\"",
    "significantChanges": false
  },
  {
    "index": 59,
    "MessageID": 99539,
    "TextENGNew": "Akasaka-san seemed to grin broadly as soon as he recognized me.",
    "significantChanges": false
  },
  {
    "index": 60,
    "MessageID": 99540,
    "TextENGNew": "Umm... Akasaka-san. You may say that, but could you suppress that bloodlust that could kill any insect that got too close to you...?",
    "significantChanges": false
  },
  {
    "index": 61,
    "MessageID": 99541,
    "TextENGNew": "\"What? Dad?!@k@vS10/40/410300980. You know Ryuunosuke-san?!\"",
    "significantChanges": false
  },
  {
    "index": 62,
    "MessageID": 99542,
    "TextENGNew": "\"You could say that.@k@vS10/13/410900010. ...Hmm? Ryuunosuke...?\"",
    "significantChanges": false
  },
  {
    "index": 63,
    "MessageID": 99543,
    "TextENGNew": "\"Oh, about that...\"",
    "significantChanges": false
  },
  {
    "index": 64,
    "MessageID": 99544,
    "TextENGNew": "I desperately tried to evade his questioning. Please, let me out of here.",
    "significantChanges": false
  },
  {
    "index": 65,
    "MessageID": 99545,
    "TextENGNew": "Miyuki-chan's eyes were open wide in a daze as she watched all this.",
    "significantChanges": false
  },
  {
    "index": 66,
    "MessageID": 99546,
    "TextENGNew": "\"Well, I've visited the neighboring town of Okinomiya several times while investigating the Great Hinamizawa Disaster.@k@vS10/13/410900012. I met Arakawa-kun a few times to discuss some old Hinamizawa-related tapes he brought with him.\"",
    "significantChanges": false
  },
  {
    "index": 67,
    "MessageID": 99547,
    "TextENGNew": "\"Is that so...?\"",
    "significantChanges": false
  },
  {
    "index": 68,
    "MessageID": 99548,
    "TextENGNew": "\"Seems like you've been doing investigating of your own, just like your father.@k@vS10/13/410900014. But even so, try not to work yourself too hard.\"",
    "significantChanges": false
  },
  {
    "index": 69,
    "MessageID": 99549,
    "TextENGNew": "\"Haah... haha. Okay.\"",
    "significantChanges": false
  },
  {
    "index": 70,
    "MessageID": 99550,
    "TextENGNew": "I tried to give a suitable retort.",
    "significantChanges": false
  },
  {
    "index": 71,
    "MessageID": 99551,
    "TextENGNew": "But the truth is... my father actually met Akasaka-san, too.",
    "significantChanges": false
  },
  {
    "index": 72,
    "MessageID": 99552,
    "TextENGNew": "When my father interviewed the survivor of the Great Hinamizawa Disaster who predicted he would \"drown to death,\" he started to grow interested in the disaster itself... and during that investigation, the two of them got to know one another.",
    "significantChanges": false
  },
  {
    "index": 73,
    "MessageID": 99553,
    "TextENGNew": "According to my father's investigation notes, Akasaka-san claimed that a resident of Hinamizawa predicted his wife's death...",
    "significantChanges": false
  },
  {
    "index": 74,
    "MessageID": 99554,
    "TextENGNew": "So, meeting up with Akasaka-san, who my father met during his own investigation in Hinamizawa, felt like an act of fate.",
    "significantChanges": false
  },
  {
    "index": 75,
    "MessageID": 99555,
    "TextENGNew": "\"Your father was a splendid reporter.@k@vS10/13/410900016. ...But you can be even better than him.\"",
    "significantChanges": false
  },
  {
    "index": 76,
    "MessageID": 99556,
    "TextENGNew": "\"...I'm not like my father.@k@vS10/62/410101708. All I'm doing is walking through life trying not to embarrass myself.\"",
    "significantChanges": false
  },
  {
    "index": 77,
    "MessageID": 99557,
    "TextENGNew": "Akasaka-san must have thought those comments were exceedingly pure for a man in his 30s like me.",
    "significantChanges": false
  },
  {
    "index": 78,
    "MessageID": 99558,
    "TextENGNew": "That's why he bitterly smiled.",
    "significantChanges": false
  },
  {
    "index": 79,
    "MessageID": 99559,
    "TextENGNew": "But there was a gentle warmth in his eyes.",
    "significantChanges": false
  },
  {
    "index": 80,
    "MessageID": 99560,
    "TextENGNew": "\"Haah... it's a small world.@k@vS10/40/410300983. Well, if I had connected to you via Dad instead of that publishing company, I probably would've met you sooner.\"",
    "significantChanges": false
  },
  {
    "index": 81,
    "MessageID": 99561,
    "TextENGNew": "\"...What do you mean, Miyuki-chan?@k@vS10/62/410101710. Who is this \"Dad\" you keep mentioning...?\"",
    "significantChanges": false
  },
  {
    "index": 82,
    "MessageID": 99562,
    "TextENGNew": "\"Huh?@k@vS10/40/410300985. Ohh, this is my father.\"",
    "significantChanges": false
  },
  {
    "index": 83,
    "MessageID": 99563,
    "TextENGNew": "\"H-huuuuuh?!\"",
    "significantChanges": false
  },
  {
    "index": 84,
    "MessageID": 99564,
    "TextENGNew": "Akasaka-san... is Miyuki-chan's... father?",
    "significantChanges": false
  },
  {
    "index": 85,
    "MessageID": 99565,
    "TextENGNew": "They're nothing alike. Not at all.",
    "significantChanges": false
  },
  {
    "index": 86,
    "MessageID": 99566,
    "TextENGNew": "How could someone as cute as Miyuki-chan be born from someone like Akasaka-san? I can't believe it!",
    "significantChanges": false
  },
  {
    "index": 87,
    "MessageID": 99567,
    "TextENGNew": "......",
    "significantChanges": false
  },
  {
    "index": 88,
    "MessageID": 99568,
    "TextENGNew": "But... looking a little closer, Akasaka-san didn't look so bad, himself.",
    "significantChanges": false
  },
  {
    "index": 89,
    "MessageID": 99569,
    "TextENGNew": "Huh...?",
    "significantChanges": false
  },
  {
    "index": 90,
    "MessageID": 99570,
    "TextENGNew": "So, the two of them really are... father and daughter...?",
    "significantChanges": false
  },
  {
    "index": 91,
    "MessageID": 99571,
    "TextENGNew": "Unbelievable. Impossible. Absolutely absurd!",
    "significantChanges": false
  },
  {
    "index": 92,
    "MessageID": 99572,
    "TextENGNew": "\"Arakawa-kun certainly is a fine young man, but...@k@vS10/13/410900018. wouldn't your husband be in tears if he knew you were running around with other men?\"",
    "significantChanges": false
  },
  {
    "index": 93,
    "MessageID": 99573,
    "TextENGNew": "\"What are you saying?@k@vS10/40/410300987. Don't be stupid. Besides, don't you have things to take care of?\"",
    "significantChanges": false
  },
  {
    "index": 94,
    "MessageID": 99574,
    "TextENGNew": "\"Hahahaha.@k@vS10/13/410900020. ...Alright, later then.\"",
    "significantChanges": false
  },
  {
    "index": 95,
    "MessageID": 99575,
    "TextENGNew": "Akasaka-san let out a small smile and bowed to me, then walked off in the direction of Mifune's corpse.",
    "significantChanges": false
  },
  {
    "index": 96,
    "MessageID": 99576,
    "TextENGNew": "......",
    "significantChanges": false
  },
  {
    "index": 97,
    "MessageID": 99577,
    "TextENGNew": "No... more importantly.",
    "significantChanges": false
  },
  {
    "index": 98,
    "MessageID": 99578,
    "TextENGNew": "Akasaka-san just said something reaaaally important just now, didn't he...?",
    "significantChanges": false
  },
  {
    "index": 99,
    "MessageID": 99579,
    "TextENGNew": "\"What...?@k@vS10/62/410101713. What was that... about your husband?\"",
    "significantChanges": false
  },
  {
    "index": 100,
    "MessageID": 99580,
    "TextENGNew": "\"...Just my father being obnoxious.\"",
    "significantChanges": false
  },
  {
    "index": 101,
    "MessageID": 99581,
    "TextENGNew": "\"No, if you're Akasaka-san's daughter...@k@vS10/62/410101715. but... your last name is Sorimachi...\"",
    "significantChanges": false
  },
  {
    "index": 102,
    "MessageID": 99582,
    "TextENGNew": "\"That's right.@k@vS10/40/410300990. I changed my name when I got married.@k@vS10/40/410300991. ...My father and I are both detectives.@k@vS10/40/410300992. And on top of that, my husband is a detective too.@k@vS10/40/410300993. ...We're a weird family.\"",
    "significantChanges": false
  },
  {
    "index": 103,
    "MessageID": 99583,
    "TextENGNew": "\"Wh-whaaaaaat?!\"",
    "significantChanges": false
  },
  {
    "index": 104,
    "MessageID": 99584,
    "TextENGNew": "Miyuki-chan lightly smiled as she said that.",
    "significantChanges": false
  },
  {
    "index": 105,
    "MessageID": 99585,
    "TextENGNew": "I, on the other hand... couldn't laugh about it.",
    "significantChanges": false
  },
  {
    "index": 106,
    "MessageID": 99586,
    "TextENGNew": "Miyuki-chan was married this whole time?!",
    "significantChanges": false
  },
  {
    "index": 107,
    "MessageID": 99587,
    "TextENGNew": "My shock must've been plain to see. Miyuki-chan deeply lowered her head and said, \"I'm sorry!\" several times in a row.",
    "significantChanges": false
  },
  {
    "index": 108,
    "MessageID": 99588,
    "TextENGNew": "\"I don't have a boyfriend, but I do have a <i>husband</i>.@k@vS10/40/410300995. At first I was just playing a joke on you, but I never really had an opportunity to come clean about it...\"",
    "significantChanges": false
  },
  {
    "index": 109,
    "MessageID": 99589,
    "TextENGNew": "...Sounds like she was planning to drop the \"Actually, I'm maaarried♪\" on me at some point and have a good laugh at my expense.",
    "significantChanges": false
  },
  {
    "index": 110,
    "MessageID": 99590,
    "TextENGNew": "But... up until now, we never really had a moment to relax...",
    "significantChanges": false
  },
  {
    "index": 111,
    "MessageID": 99591,
    "TextENGNew": "The timing just wasn't appropriate to reveal it and laugh at the \"Whaaat, really?\" reaction...",
    "significantChanges": false
  },
  {
    "index": 112,
    "MessageID": 99592,
    "TextENGNew": "\"Um... Ryuunosuke-san, is there a chance that you...?\"",
    "significantChanges": false
  },
  {
    "index": 113,
    "MessageID": 99593,
    "TextENGNew": "As she said that,",
    "significantChanges": false
  },
  {
    "index": 114,
    "MessageID": 99594,
    "TextENGNew": "Miyuki-chan looked terribly distraught, afraid to face me directly.",
    "significantChanges": false
  },
  {
    "index": 115,
    "MessageID": 99595,
    "TextENGNew": "She wasn't trying to lead me around... but she seems terribly upset that she might've carelessly hurt me.",
    "significantChanges": false
  },
  {
    "index": 116,
    "MessageID": 99596,
    "TextENGNew": "Well... I'd be lying if I said it didn't hurt...",
    "significantChanges": false
  },
  {
    "index": 117,
    "MessageID": 99597,
    "TextENGNew": "Still, her intentions weren't malicious, so it was my duty as a man to make things easier on her. ...Probably.",
    "significantChanges": false
  },
  {
    "index": 118,
    "MessageID": 99598,
    "TextENGNew": "\"N-nooooo, nothing like that!\"",
    "significantChanges": false
  },
  {
    "index": 119,
    "MessageID": 99599,
    "TextENGNew": "\"I'm just really surprised to learn that you're Akasaka-san's daughter, Miyuki-chan. It really is a small world.@k@vS10/62/410101719. So really, there's nothing for you to be worried about!\"",
    "significantChanges": false
  },
  {
    "index": 120,
    "MessageID": 99600,
    "TextENGNew": "\"Really?\"",
    "significantChanges": false
  },
  {
    "index": 121,
    "MessageID": 99601,
    "TextENGNew": "\"R-really!\"",
    "significantChanges": false
  },
  {
    "index": 122,
    "MessageID": 99602,
    "TextENGNew": "\"...@k@vS10/40/410300999.Thank goodness♪.\"",
    "significantChanges": false
  },
  {
    "index": 123,
    "MessageID": 99603,
    "TextENGNew": "Miyuki-chan flashed me a big grin.",
    "significantChanges": false
  },
  {
    "index": 124,
    "MessageID": 99604,
    "TextENGNew": "I... had no choice but to nod to her with a vague smile.",
    "significantChanges": false
  },
  {
    "index": 125,
    "MessageID": 99605,
    "TextENGNew": "Aah, goodbye my innocent love.",
    "significantChanges": false
  },
  {
    "index": 126,
    "MessageID": 99606,
    "TextENGNew": "Well, it's not like it really began in the first place.",
    "significantChanges": false
  },
  {
    "index": 127,
    "MessageID": 99607,
    "TextENGNew": "\"...Ah, this is bad.@k@vS10/40/410301001. It'll cause trouble if you guys stay here... so why don't you get going, Ryuunosuke-san?\"",
    "significantChanges": false
  },
  {
    "index": 128,
    "MessageID": 99608,
    "TextENGNew": "\"Huh?\"",
    "significantChanges": false
  },
  {
    "index": 129,
    "MessageID": 99609,
    "TextENGNew": "\"I've got a lot to do here, so I won't be able to head back today.@k@vS10/40/410301003. Leave everything to the police from here on out!\"",
    "significantChanges": false
  },
  {
    "index": 130,
    "MessageID": 99610,
    "TextENGNew": "Miyuki-chan pushed me by the back, trying to drive me away.",
    "significantChanges": false
  },
  {
    "index": 131,
    "MessageID": 99611,
    "TextENGNew": "It certainly would be a bother to stick around in a place where police are conducting on-site investigations and interrogations.",
    "significantChanges": false
  },
  {
    "index": 132,
    "MessageID": 99612,
    "TextENGNew": "At that point, I realized that Sonozaki-san and Otobe had long since disappeared.",
    "significantChanges": false
  },
  {
    "index": 133,
    "MessageID": 99613,
    "TextENGNew": "\"Alright... later, Miyuki-chan...\"",
    "significantChanges": false
  },
  {
    "index": 134,
    "MessageID": 99614,
    "TextENGNew": "\"Ryuunosuke-san...@k@vS10/40/410301005. Thanks... for everything.\"",
    "significantChanges": false
  },
  {
    "index": 135,
    "MessageID": 99615,
    "TextENGNew": "Miyuki-chan deeply bowed her head.",
    "significantChanges": false
  },
  {
    "index": 136,
    "MessageID": 99616,
    "TextENGNew": "I lightly lowered my head in response, then headed out of the back room.",
    "significantChanges": false
  },
  {
    "index": 137,
    "MessageID": 99617,
    "TextENGNew": "Once I reached the gate, I took one more look toward the back room... and saw Miyuki-chan standing on the side, smiling and waving to me as she watched me head out.",
    "significantChanges": false
  },
  {
    "index": 138,
    "MessageID": 99618,
    "TextENGNew": "......",
    "significantChanges": false
  },
  {
    "index": 139,
    "MessageID": 99619,
    "TextENGNew": "I was a little out of touch (or slow?) on the subject of romance, and I was led astray... but, yeah, she's a good girl.",
    "significantChanges": false
  },
  {
    "index": 140,
    "MessageID": 99620,
    "TextENGNew": "I'll send her an email next time I have an opportunity.",
    "significantChanges": false
  },
  {
    "index": 141,
    "MessageID": 99621,
    "TextENGNew": "I'd be proud to consider her a \"friend\" who endured this situation without falling into a bad relationship...",
    "significantChanges": false
  },
  {
    "index": 142,
    "MessageID": 99622,
    "TextENGNew": "Several patrol cars were parked outside the gate.",
    "significantChanges": false
  },
  {
    "index": 143,
    "MessageID": 99623,
    "TextENGNew": "So, which way did they go...?",
    "significantChanges": false
  },
  {
    "index": 144,
    "MessageID": 99624,
    "TextENGNew": "For now, I decided to walk in the direction I came from.",
    "significantChanges": false
  },
  {
    "index": 145,
    "MessageID": 99625,
    "TextENGNew": "Before long, I found Otobe and Sonozaki-san sitting on a big stone by the side of the road, waiting for me.",
    "significantChanges": false
  },
  {
    "index": 146,
    "MessageID": 99626,
    "TextENGNew": "\"Otobe...! Sonozaki-san...!\"",
    "significantChanges": false
  },
  {
    "index": 147,
    "MessageID": 99627,
    "TextENGNew": "I ran toward them.",
    "significantChanges": false
  },
  {
    "index": 148,
    "MessageID": 99628,
    "TextENGNew": "Then, a familiar girl came walking this way from the other end of the street.",
    "significantChanges": false
  },
  {
    "index": 149,
    "MessageID": 99629,
    "TextENGNew": "\"Towada-san!@k@vS10/41/410201000. ...I'm glad you're safe!\"",
    "significantChanges": false
  },
  {
    "index": 150,
    "MessageID": 99630,
    "TextENGNew": "\"You too, Otobe-kun...@k@vS10/42/410600677. The most important thing is that everyone is safe.\"",
    "significantChanges": false
  },
  {
    "index": 151,
    "MessageID": 99631,
    "TextENGNew": "Otobe grabbed Towada-san's hand and gave her a huge smile to celebrate that they were both alive.",
    "significantChanges": false
  },
  {
    "index": 152,
    "MessageID": 99632,
    "TextENGNew": "\"...Oh, Sonozaki-san, let me return the gun you lent me.@k@vS10/42/410600679. Thank you very much.\"",
    "significantChanges": false
  },
  {
    "index": 153,
    "MessageID": 99633,
    "TextENGNew": "\"Oh... sure.\"",
    "significantChanges": false
  },
  {
    "index": 154,
    "MessageID": 99634,
    "TextENGNew": "Towada-san handed the gun she borrowed from Mion-san over to Shion-san.",
    "significantChanges": false
  },
  {
    "index": 155,
    "MessageID": 99635,
    "TextENGNew": "Shion-san seemed a bit confused, but she decided to leave it at that since a proper explanation would've taken far too long.",
    "significantChanges": false
  },
  {
    "index": 156,
    "MessageID": 99636,
    "TextENGNew": "Then, once we realized that Towada-san came to see us off, we all turned toward her.",
    "significantChanges": false
  },
  {
    "index": 157,
    "MessageID": 99637,
    "TextENGNew": "\"...That's right.@k@vS10/41/410201002. Umm, Towada-san... what are you planning to do from here on?\"",
    "significantChanges": false
  },
  {
    "index": 158,
    "MessageID": 99638,
    "TextENGNew": "\"...After everyone left, I faced Takumi-kun and came to a decision.@k@vS10/42/410600681. ...It's time to start over and live a new life.\"",
    "significantChanges": false
  },
  {
    "index": 159,
    "MessageID": 99639,
    "TextENGNew": "\"And, in order to make things right... I'm going to turn myself in.\"",
    "significantChanges": false
  },
  {
    "index": 160,
    "MessageID": 99640,
    "TextENGNew": "\"Oh, really...?\"",
    "significantChanges": false
  },
  {
    "index": 161,
    "MessageID": 99641,
    "TextENGNew": "\"Same here... I think I'm ready to start a new life.@k@vS10/41/410201004. I'll find a way to repay my debts.@k@vS10/41/410201005. I'll talk things over with my parents properly.@k@vS10/41/410201006. If I search hard enough, I'm sure I'll be able to find a path forward.\"",
    "significantChanges": false
  },
  {
    "index": 162,
    "MessageID": 99642,
    "TextENGNew": "\"...It probably won't be easy... but I've decided. I'm not going to run away anymore.\"",
    "significantChanges": false
  },
  {
    "index": 163,
    "MessageID": 99643,
    "TextENGNew": "...Life is like a tube of toothpaste.",
    "significantChanges": false
  },
  {
    "index": 164,
    "MessageID": 99644,
    "TextENGNew": "...You have to squeeze every last drop out of it.",
    "significantChanges": false
  },
  {
    "index": 165,
    "MessageID": 99645,
    "TextENGNew": "I thought back on what Mion-san said earlier.",
    "significantChanges": false
  },
  {
    "index": 166,
    "MessageID": 99646,
    "TextENGNew": "I certainly agree with that assessment. Rather than hesitating, the best choice at any given time is to simply do whatever you can...",
    "significantChanges": false
  },
  {
    "index": 167,
    "MessageID": 99647,
    "TextENGNew": "\"Oh, Arakawa-san.@k@vS10/41/410201009. After I've cleaned everything up... would you consider hiring me as your assistant?\"",
    "significantChanges": false
  },
  {
    "index": 168,
    "MessageID": 99648,
    "TextENGNew": "\"Don't be stupid. I'm not nearly that important.\"",
    "significantChanges": false
  },
  {
    "index": 169,
    "MessageID": 99649,
    "TextENGNew": "\"Huh?\"",
    "significantChanges": false
  },
  {
    "index": 170,
    "MessageID": 99650,
    "TextENGNew": "\"I was lying about being a famous writer. It's not true.@k@vS10/62/410101728. I can hardly make the rent on my run-down apartment. I was even thinking of giving up the writing business.\"",
    "significantChanges": false
  },
  {
    "index": 171,
    "MessageID": 99651,
    "TextENGNew": "\"Seriously?!\"",
    "significantChanges": false
  },
  {
    "index": 172,
    "MessageID": 99652,
    "TextENGNew": "I scratched my head. ...His dramatic reaction was a little embarrassing.",
    "significantChanges": false
  },
  {
    "index": 173,
    "MessageID": 99653,
    "TextENGNew": "\"Well, I'm half-kidding.@k@vS10/62/410101730. But... if there's one thing I learned, it's that I've really come to appreciate Hinamizawa.\"",
    "significantChanges": false
  },
  {
    "index": 174,
    "MessageID": 99654,
    "TextENGNew": "\"The truth is... after everything that's happened, I've started to like it.@k@vS10/62/410101732. Regardless of everything else, I heard the voice of the dead for the first time ever!\"",
    "significantChanges": false
  },
  {
    "index": 175,
    "MessageID": 99655,
    "TextENGNew": "\"...I was probably taking it too easy.@k@vS10/62/410101734. I just half-assed work, only caring if I was having fun, so I don't know what the future has in store for me.\"",
    "significantChanges": false
  },
  {
    "index": 176,
    "MessageID": 99656,
    "TextENGNew": "......",
    "significantChanges": false
  },
  {
    "index": 177,
    "MessageID": 99657,
    "TextENGNew": "But... I won't hesitate any longer.",
    "significantChanges": false
  },
  {
    "index": 178,
    "MessageID": 99658,
    "TextENGNew": "It seems like... I finally managed to find my way.",
    "significantChanges": false
  },
  {
    "index": 179,
    "MessageID": 99659,
    "TextENGNew": "\"I've also come to a conclusion.@k@vS10/62/410101736. I'm certain that the spirits of the dead persist even when the body is destroyed.@k@vS10/62/410101737. ...And sometimes, they need to borrow the body of a human to carry out their will.\"",
    "significantChanges": false
  },
  {
    "index": 180,
    "MessageID": 99660,
    "TextENGNew": "\"I'm glad I met all of you.@k@vS10/62/410101739. ...And I think I'll keep going with this line of work.@k@vS10/62/410101740. Some day, I really will be able to say I'm a famous writer and actually mean it.\"",
    "significantChanges": false
  },
  {
    "index": 181,
    "MessageID": 99661,
    "TextENGNew": "\"Arakawa-san...\"",
    "significantChanges": false
  },
  {
    "index": 182,
    "MessageID": 99662,
    "TextENGNew": "\"...Well, feel free to contact me if that day ever arrives.@k@vS10/62/410101742. Although, the pay isn't great and the job demands a lot of running around.\"",
    "significantChanges": false
  },
  {
    "index": 183,
    "MessageID": 99663,
    "TextENGNew": "\"...Got it!\"",
    "significantChanges": false
  },
  {
    "index": 184,
    "MessageID": 99664,
    "TextENGNew": "\"But I'll have to give up on this story.\"",
    "significantChanges": false
  },
  {
    "index": 185,
    "MessageID": 99665,
    "TextENGNew": "\"Between the yakuza power struggle and the dead crying and apologizing to the living, the Weekly Seven would never publish this... My head is starting to hurt just thinking about what to do with this.\"",
    "significantChanges": false
  },
  {
    "index": 186,
    "MessageID": 99666,
    "TextENGNew": "\"Ahahaha...\"",
    "significantChanges": false
  },
  {
    "index": 187,
    "MessageID": 99667,
    "TextENGNew": "Otobe quietly chuckled.",
    "significantChanges": false
  },
  {
    "index": 188,
    "MessageID": 99668,
    "TextENGNew": "Huh... so he can smile like this...",
    "significantChanges": false
  },
  {
    "index": 189,
    "MessageID": 99669,
    "TextENGNew": "Otobe had a bright, youthful smile on his face.",
    "significantChanges": false
  },
  {
    "index": 190,
    "MessageID": 99670,
    "TextENGNew": "Then, Towada-san bowed her head to us... before heading out to see Miyuki-chan.",
    "significantChanges": false
  },
  {
    "index": 191,
    "MessageID": 99671,
    "TextENGNew": "After watching her confidently walk off, the rest of us turned to one another... and quietly nodded.",
    "significantChanges": false
  },
  {
    "index": 192,
    "MessageID": 99672,
    "TextENGNew": "\"You guys are a long way from town.@k@vS10/44/410500058. I'll drop you off there.\"",
    "significantChanges": false
  },
  {
    "index": 193,
    "MessageID": 99673,
    "TextENGNew": "Along with Shion-san's voice, I heard the sound of a car horn.",
    "significantChanges": false
  },
  {
    "index": 194,
    "MessageID": 99674,
    "TextENGNew": "A black car had pulled up right behind us without me even realizing it.",
    "significantChanges": false
  },
  {
    "index": 195,
    "MessageID": 99675,
    "TextENGNew": "Shion-san got out of there, and a man whose appearance betrayed his aura walked over to us as if guiding her.",
    "significantChanges": false
  },
  {
    "index": 196,
    "MessageID": 99676,
    "TextENGNew": "...Sensing his power, I braced myself for a moment.",
    "significantChanges": false
  },
  {
    "index": 197,
    "MessageID": 99677,
    "TextENGNew": "\"Oh, this is Kasai.@k@vS10/44/410500060. Don't worry about him.\"",
    "significantChanges": false
  },
  {
    "index": 198,
    "MessageID": 99678,
    "TextENGNew": "\"Y-yes, ma'am...\"",
    "significantChanges": false
  },
  {
    "index": 199,
    "MessageID": 99679,
    "TextENGNew": "I couldn't help but give an overly formal response. ...What am I doing?",
    "significantChanges": false
  },
  {
    "index": 200,
    "MessageID": 99680,
    "TextENGNew": "Then, we climbed into the elegant car and Kasai-san drove us down a straight road leading to the village.",
    "significantChanges": false
  },
  {
    "index": 201,
    "MessageID": 99681,
    "TextENGNew": "Otobe quickly fell asleep. He must've felt relieved.",
    "significantChanges": false
  },
  {
    "index": 202,
    "MessageID": 99682,
    "TextENGNew": "I idly gazed out the window.",
    "significantChanges": false
  },
  {
    "index": 203,
    "MessageID": 99683,
    "TextENGNew": "Then... at the foot of the rough mountains, a massive pile of rubble came into view.",
    "significantChanges": false
  },
  {
    "index": 204,
    "MessageID": 99684,
    "TextENGNew": "\"What is that...?@k@vS10/62/410101747. It looks like the ruins of some collapsed building...?\"",
    "significantChanges": false
  },
  {
    "index": 205,
    "MessageID": 99685,
    "TextENGNew": "\"It's the remains of a school.@k@vS10/44/410500062. It's been left untouched since the explosion during the hostage incident.@k@vS10/44/410500063. ...Kasai, could you stop here?\"",
    "significantChanges": false
  },
  {
    "index": 206,
    "MessageID": 99686,
    "TextENGNew": "Kasai-san seemed to completely understand. He parked the car along the side of the ruins, then opened the rear passenger door.",
    "significantChanges": false
  },
  {
    "index": 207,
    "MessageID": 99687,
    "TextENGNew": "Shion-san slowly emerged from the car... and let out a deep sigh.",
    "significantChanges": false
  },
  {
    "index": 208,
    "MessageID": 99688,
    "TextENGNew": "\"This is where everyone died...@k@vS10/44/410500065. I lost my sister, my friends, and everything in that incident over 20 years ago.@k@vS10/44/410500066. The only survivors were myself and the boy Sis liked.@k@vS10/44/410500067. ...But even he died shortly afterwards.\"",
    "significantChanges": false
  },
  {
    "index": 209,
    "MessageID": 99689,
    "TextENGNew": "\"......\"",
    "significantChanges": false
  },
  {
    "index": 210,
    "MessageID": 99690,
    "TextENGNew": "\"That's why I thought...@k@vS10/44/410500069. I should've died with them in the explosion that day.@k@vS10/44/410500070. All this time, I thought I was left alone.@k@vS10/44/410500071. ...Always.\"",
    "significantChanges": false
  },
  {
    "index": 211,
    "MessageID": 99691,
    "TextENGNew": "\"Shion-san...\"",
    "significantChanges": false
  },
  {
    "index": 212,
    "MessageID": 99692,
    "TextENGNew": "Shion-san forlornly gazed on as the wind blew through the mountain of rubble.",
    "significantChanges": false
  },
  {
    "index": 213,
    "MessageID": 99693,
    "TextENGNew": "Has she been tormented for the last 20 years by the lonely thought that she was the one left behind...?",
    "significantChanges": false
  },
  {
    "index": 214,
    "MessageID": 99694,
    "TextENGNew": "She abandoned the name Shion and lived her life as Mion Sonozaki to protect the Sonozaki family.",
    "significantChanges": false
  },
  {
    "index": 215,
    "MessageID": 99695,
    "TextENGNew": "Enduring that for all this time... must've been so painful.",
    "significantChanges": false
  },
  {
    "index": 216,
    "MessageID": 99696,
    "TextENGNew": "\"......Your sister once told us,@k@vS10/62/410101751. \"Life is like a tube of toothpaste.@k@vS10/62/410101752. You have to squeeze every last drop out of it.\"\"",
    "significantChanges": false
  },
  {
    "index": 217,
    "MessageID": 99697,
    "TextENGNew": "\"Sis said that...?\"",
    "significantChanges": false
  },
  {
    "index": 218,
    "MessageID": 99698,
    "TextENGNew": "\"Ahahahahahaha, that sounds like something she'd say!\"",
    "significantChanges": false
  },
  {
    "index": 219,
    "MessageID": 99699,
    "TextENGNew": "Otobe came crawling out of the car. Shion-san's booming laughter must've woken him up.",
    "significantChanges": false
  },
  {
    "index": 220,
    "MessageID": 99700,
    "TextENGNew": "Shion-san seemed lost in thought while gazing at his face... then, once he came closer she patted him on the head.",
    "significantChanges": false
  },
  {
    "index": 221,
    "MessageID": 99701,
    "TextENGNew": "\"...Eh? Shion-san?\"",
    "significantChanges": false
  },
  {
    "index": 222,
    "MessageID": 99702,
    "TextENGNew": "\"Live your life unwaveringly!@k@vS10/44/410500075. I'll do the same,@k@vS10/44/410500076. even if every day is full of blood and gunpowder! Hehehe.\"",
    "significantChanges": false
  },
  {
    "index": 223,
    "MessageID": 99703,
    "TextENGNew": "\"Mgh...\"",
    "significantChanges": false
  },
  {
    "index": 224,
    "MessageID": 99704,
    "TextENGNew": "Otobe suddenly seemed to be embarrassed about a woman stroking his head. His face turned red.",
    "significantChanges": false
  },
  {
    "index": 225,
    "MessageID": 99705,
    "TextENGNew": "When Shion-san saw that, she quietly muttered to herself.",
    "significantChanges": false
  },
  {
    "index": 226,
    "MessageID": 99706,
    "TextENGNew": "\"You look so much like Satoshi-kun...\"",
    "significantChanges": false
  },
  {
    "index": 227,
    "MessageID": 99707,
    "TextENGNew": "\"Huh?\"",
    "significantChanges": false
  },
  {
    "index": 228,
    "MessageID": 99708,
    "TextENGNew": "\"...It's nothing.\"",
    "significantChanges": false
  },
  {
    "index": 229,
    "MessageID": 99709,
    "TextENGNew": "Shion-san turned away from us and gazed at the school while playing with her hair in her fingertips.",
    "significantChanges": false
  },
  {
    "index": 230,
    "MessageID": 99710,
    "TextENGNew": "\"For a moment there, you reminded me of an old friend.@k@vS10/44/410500080. There's a bit of a resemblance.@k@vS10/44/410500081. How would I describe him? ...Yeah, he was a good guy.\"",
    "significantChanges": false
  },
  {
    "index": 231,
    "MessageID": 99711,
    "TextENGNew": "\"So, did this Satoshi guy also pass away in this inci...?\"",
    "significantChanges": false
  },
  {
    "index": 232,
    "MessageID": 99712,
    "TextENGNew": "\"Alright, that's enough idle chatter.\"",
    "significantChanges": false
  },
  {
    "index": 233,
    "MessageID": 99713,
    "TextENGNew": "\"With this bell, I can end this conflict in an instant.@k@vS10/44/410500084. And I need to settle the score with those Oumi punks who tried to take advantage of all this chaos.\"",
    "significantChanges": false
  },
  {
    "index": 234,
    "MessageID": 99714,
    "TextENGNew": "Although it may still be a while longer until my work is complete...",
    "significantChanges": false
  },
  {
    "index": 235,
    "MessageID": 99715,
    "TextENGNew": "Shion-san whispered that, then turned back this way... The face of the person who had muttered \"Satoshi-kun\" had completely vanished.",
    "significantChanges": false
  },
  {
    "index": 236,
    "MessageID": 99716,
    "TextENGNew": "\"Ah, Shion-san...\"",
    "significantChanges": false
  },
  {
    "index": 237,
    "MessageID": 99717,
    "TextENGNew": "\"What is it?@k@vS10/44/410500086. If you take too long, I'll leave you behind.\"",
    "significantChanges": false
  },
  {
    "index": 238,
    "MessageID": 99718,
    "TextENGNew": "\"...Shion-san, there's something I absolutely must tell you here.@k@vS10/41/410201020. ...Before leaving Hinamizawa.\"",
    "significantChanges": false
  },
  {
    "index": 239,
    "MessageID": 99719,
    "TextENGNew": "\"...?\"",
    "significantChanges": false
  },
  {
    "index": 240,
    "MessageID": 99720,
    "TextENGNew": "\"The very last thing Mion-san said to me.@k@vS10/41/410201022. She wanted you to hear this, Shion-san...\"",
    "significantChanges": false
  },
  {
    "index": 241,
    "MessageID": 99721,
    "TextENGNew": "\"Huh...?\"",
    "significantChanges": false
  },
  {
    "index": 242,
    "MessageID": 99722,
    "TextENGNew": "Shion-san stopped in her tracks.",
    "significantChanges": false
  },
  {
    "index": 243,
    "MessageID": 99723,
    "TextENGNew": "\"I have... one more favor to ask...\"",
    "significantChanges": false
  },
  {
    "index": 244,
    "MessageID": 99724,
    "TextENGNew": "I recalled the moment just before Mion Sonozaki's death, when she requested something of Otobe.",
    "significantChanges": false
  },
  {
    "index": 245,
    "MessageID": 99725,
    "TextENGNew": "Come to think of it... what did she ask him?",
    "significantChanges": false
  },
  {
    "index": 246,
    "MessageID": 99726,
    "TextENGNew": "\"Mion-san said... \"I hope... we can be twins again next time...\"@k@vS10/41/410201024. That's what she wanted you to hear.\"",
    "significantChanges": false
  },
  {
    "index": 247,
    "MessageID": 99727,
    "TextENGNew": "\"...!\"",
    "significantChanges": false
  },
  {
    "index": 248,
    "MessageID": 99728,
    "TextENGNew": "\"Hang in there... Mion.@k@vS10/44/410500090. I'll do my best as Shion.\"",
    "significantChanges": false
  },
  {
    "index": 249,
    "MessageID": 99729,
    "TextENGNew": "\"......Yeah.@k@vS10/43/410400787. ......Thanks,@k@vS10/43/410400788. Shion.\"",
    "significantChanges": false
  },
  {
    "index": 250,
    "MessageID": 99730,
    "TextENGNew": "\"Do your best, Mion.@k@vS10/44/410500092. If you run into any trouble, feel free to consult with me any time.@k@vS10/44/410500093. That's how it's always been for us.@k@vS10/44/410500094. And that'll never change.\"",
    "significantChanges": false
  },
  {
    "index": 251,
    "MessageID": 99731,
    "TextENGNew": "\"...Yeah.@k@vS10/43/410400790. ...Yeah.\"",
    "significantChanges": false
  },
  {
    "index": 252,
    "MessageID": 99732,
    "TextENGNew": "......",
    "significantChanges": false
  },
  {
    "index": 253,
    "MessageID": 99733,
    "TextENGNew": "Sheesh... that's seriously what you chose to say at the bitter end?",
    "significantChanges": false
  },
  {
    "index": 254,
    "MessageID": 99734,
    "TextENGNew": "Even though she helped out back then, she's always butting in where she doesn't belong... treating me like a child.",
    "significantChanges": false
  },
  {
    "index": 255,
    "MessageID": 99735,
    "TextENGNew": "I'm an adult now, you know? Much older than you were. Seriously... I can't believe your last words were something so naive...",
    "significantChanges": false
  },
  {
    "index": 256,
    "MessageID": 99736,
    "TextENGNew": "......",
    "significantChanges": false
  },
  {
    "index": 257,
    "MessageID": 99737,
    "TextENGNew": "And the word \"next\"... made me sad. Because you reminded me that you're already gone.",
    "significantChanges": false
  },
  {
    "index": 258,
    "MessageID": 99738,
    "TextENGNew": "I wasn't interested in reminiscing about the old days. ...I wanted to talk about those memories with you.",
    "significantChanges": false
  },
  {
    "index": 259,
    "MessageID": 99739,
    "TextENGNew": "I wanted to keep you by my side forever... \"Sis\"...!!",
    "significantChanges": false
  },
  {
    "index": 260,
    "MessageID": 99740,
    "TextENGNew": "\"...Sis...\"",
    "significantChanges": false
  },
  {
    "index": 261,
    "MessageID": 99741,
    "TextENGNew": "Tears started to well up in Shion-san's eyes.",
    "significantChanges": false
  },
  {
    "index": 262,
    "MessageID": 99742,
    "TextENGNew": "\"Shion-san...\"",
    "significantChanges": false
  },
  {
    "index": 263,
    "MessageID": 99743,
    "TextENGNew": "\"Ahaha, ahahahahahah!@k@vS10/44/410500097. Whaaat? How could she say something so obvious?!\"",
    "significantChanges": false
  },
  {
    "index": 264,
    "MessageID": 99744,
    "TextENGNew": "Shion-san pulled the Tamahajiki sword from its sheath and thrust the blade into the ground near the former school building.",
    "significantChanges": false
  },
  {
    "index": 265,
    "MessageID": 99745,
    "TextENGNew": "\"Thanks, Sis...!\"",
    "significantChanges": false
  },
  {
    "index": 266,
    "MessageID": 99746,
    "TextENGNew": "Then... Shion-san turned and didn't look back.",
    "significantChanges": false
  },
  {
    "index": 267,
    "MessageID": 99747,
    "TextENGNew": "Somewhere among the ruins, a single playing card fluttered in the wind.",
    "significantChanges": false
  },
  {
    "index": 268,
    "MessageID": 99748,
    "TextENGNew": "......",
    "significantChanges": false
  },
  {
    "index": 269,
    "MessageID": 99749,
    "TextENGNew": "That card probably dated back to the days when Mion Sonozaki played at this school.",
    "significantChanges": false
  },
  {
    "index": 270,
    "MessageID": 99750,
    "TextENGNew": "The playing card gently fell to the ground, nestled next to the sword.",
    "significantChanges": false
  },
  {
    "index": 271,
    "MessageID": 99751,
    "TextENGNew": "\"...Thanks, Sonozaki-san.@k@vS10/62/410101757. And farewell, Hinamizawa.\"",
    "significantChanges": false
  },
  {
    "index": 272,
    "MessageID": 99752,
    "TextENGNew": "Then I, too, started walking without looking back.",
    "significantChanges": false
  },
  {
    "index": 273,
    "MessageID": 99753,
    "TextENGNew": "All the while, swearing in my heart that I'd never look back on the past.",
    "significantChanges": false
  },
  {
    "index": 274,
    "MessageID": 99754,
    "TextENGNew": "Otobe and Towada-san had already started walking forward.",
    "significantChanges": false
  },
  {
    "index": 275,
    "MessageID": 99755,
    "TextENGNew": "The car Kasai-san drove us here in slowly descended the mountain path.",
    "significantChanges": false
  },
  {
    "index": 276,
    "MessageID": 99756,
    "TextENGNew": "......",
    "significantChanges": false
  },
  {
    "index": 277,
    "MessageID": 99757,
    "TextENGNew": "Everyone here started walking toward their own separate future.",
    "significantChanges": false
  },
  {
    "index": 278,
    "MessageID": 99758,
    "TextENGNew": "All of us starting at a disadvantage.",
    "significantChanges": false
  },
  {
    "index": 279,
    "MessageID": 99759,
    "TextENGNew": "Otobe's future involved repaying a debt he could never pay off alone.",
    "significantChanges": false
  },
  {
    "index": 280,
    "MessageID": 99760,
    "TextENGNew": "Towada-san's future included being arrested and sent to prison.",
    "significantChanges": false
  },
  {
    "index": 281,
    "MessageID": 99761,
    "TextENGNew": "Sonozaki-san and Kasai-san's future involved fighting to protect the future of the Sonozaki Group.",
    "significantChanges": false
  },
  {
    "index": 282,
    "MessageID": 99762,
    "TextENGNew": "And my future... is to start building something meaningful in my day to day life, while panicking about the uncertainty of tomorrow.",
    "significantChanges": false
  },
  {
    "index": 283,
    "MessageID": 99763,
    "TextENGNew": "......",
    "significantChanges": false
  },
  {
    "index": 284,
    "MessageID": 99764,
    "TextENGNew": "None of us will have it easy in the future.",
    "significantChanges": false
  },
  {
    "index": 285,
    "MessageID": 99765,
    "TextENGNew": "But regardless, we'll keep walking forward. Fighting alone against our fate, for the right to say we \"lived.\"",
    "significantChanges": false
  },
  {
    "index": 286,
    "MessageID": 99766,
    "TextENGNew": "Mion Sonozaki... and... Hinamizawa village...",
    "significantChanges": false
  },
  {
    "index": 287,
    "MessageID": 99767,
    "TextENGNew": "Farewell.",
    "significantChanges": false
  },
  {
    "index": 288,
    "MessageID": 99768,
    "TextENGNew": "And... thank you.",
    "significantChanges": false
  },
  {
    "index": 289,
    "MessageID": 99769,
    "TextENGNew": "A refreshing blue sky was spread out beyond the mountains, shining the light of hope down on our future.",
    "significantChanges": false
  }
]
